deepmorpheus/__init__.py
deepmorpheus/dataset.py
deepmorpheus/model.py
deepmorpheus/tag.py
deepmorpheus/train.py
deepmorpheus/util.py
deepmorpheus-0.2.3.dist-info/LICENSE
deepmorpheus-0.2.3.dist-info/METADATA
deepmorpheus-0.2.3.dist-info/WHEEL
deepmorpheus-0.2.3.dist-info/top_level.txt
deepmorpheus-0.2.3.dist-info/RECORD
