Metadata-Version: 2.1
Name: deepmorpheus
Version: 0.2.3
Summary: Morphological tagger for Ancient Greek and Latin using deep learning
Home-page: https://github.com/offerijns/deepmorpheus
Author: Mees Gelein, Jeroen Offerijns
License: UNKNOWN
Platform: UNKNOWN
Classifier: Programming Language :: Python :: 3
Classifier: License :: OSI Approved :: MIT License
Classifier: Operating System :: OS Independent
Requires-Python: >=3.6
Requires-Dist: pyconll (==2.2.1)
Requires-Dist: requests (==2.23.0)
Requires-Dist: pytorch-lightning (==0.8.4)
